meomaya/__init__.py
meomaya/__main__.py
meomaya/api/__init__.py
meomaya/api/server.py
meomaya/audio/__init__.py
meomaya/audio/pipeline.py
meomaya/cli/__init__.py
meomaya/cli/meomaya_cmd.py
meomaya/core/__init__.py
meomaya/core/hardware.py
meomaya/core/hf_local.py
meomaya/core/model_registry.py
meomaya/core/modelify.py
meomaya/core/normalizer.py
meomaya/core/parser.py
meomaya/core/tagger.py
meomaya/core/tokenizer.py
meomaya/core/utils.py
meomaya/data/__init__.py
meomaya/data/corpus_loader.py
meomaya/examples/full_nlp_workflow_demo.py
meomaya/image/__init__.py
meomaya/image/pipeline.py
meomaya/ml/__init__.py
meomaya/ml/classifier.py
meomaya/ml/vectorizer.py
meomaya/scripts/eval_classifier.py
meomaya/scripts/train_classifier.py
meomaya/tests/test_all.py
meomaya/text/__init__.py
meomaya/text/pipeline.py
meomaya/video/__init__.py
meomaya/video/pipeline.py
meox-1.dist-info/METADATA
meox-1.dist-info/WHEEL
meox-1.dist-info/top_level.txt
meox-1.dist-info/RECORD
