Metadata-Version: 2.4
Name: MeoX
Version: 1
Summary: MeoX — a pure-Python, hardware-aware NLP framework with modular pipelines
Author-email: Kashyapsinh Gohil <Kagohil000@gmail.com>
License: Polyform Noncommercial 1.0.0
Project-URL: Homepage, https://kashyapsinh-gohil.github.io/MeoMaya-Info/
Requires-Python: >=3.11
Requires-Dist: nltk>=3.8.1
Requires-Dist: indic-nlp-library>=0.81
Requires-Dist: cython>=0.29.32
Requires-Dist: click>=8.1.3
Requires-Dist: fastapi>=0.111.0
Requires-Dist: uvicorn>=0.30.0
Requires-Dist: transformers>=4.41.0
Requires-Dist: torch>=2.3.0
